e3x/__init__.py
e3x/config.py
e3x/util.py
e3x/version.py
e3x/nn/__init__.py
e3x/nn/activations.py
e3x/nn/features.py
e3x/nn/initializers.py
e3x/nn/modules.py
e3x/nn/wrappers.py
e3x/nn/functions/__init__.py
e3x/nn/functions/bernstein.py
e3x/nn/functions/chebyshev.py
e3x/nn/functions/cutoff.py
e3x/nn/functions/damping.py
e3x/nn/functions/gaussian.py
e3x/nn/functions/mappings.py
e3x/nn/functions/switch.py
e3x/nn/functions/trigonometric.py
e3x/nn/functions/window.py
e3x/ops/__init__.py
e3x/ops/helpers.py
e3x/ops/indexed.py
e3x/ops/safe.py
e3x/so3/__init__.py
e3x/so3/_clebsch_gordan_lut.npz
e3x/so3/_clebsch_gordan_lut.py
e3x/so3/_common.py
e3x/so3/_delley_grids.npz
e3x/so3/_lebedev_grids.npz
e3x/so3/_lookup_table_generation_utility.py
e3x/so3/_normalization.py
e3x/so3/_spherical_harmonics_lut.npz
e3x/so3/_spherical_harmonics_lut.py
e3x/so3/_symbolic.py
e3x/so3/_tensor_conversion_lut.npz
e3x/so3/_tensor_conversion_lut.py
e3x/so3/_wigner_d_lut.npz
e3x/so3/_wigner_d_lut.py
e3x/so3/irreps.py
e3x/so3/quadrature.py
e3x/so3/rotations.py
e3x-1.0.2.dist-info/LICENSE
e3x-1.0.2.dist-info/WHEEL
e3x-1.0.2.dist-info/METADATA
e3x-1.0.2.dist-info/RECORD
