Metadata-Version: 2.1
Name: e3x
Version: 1.0.2
Summary: JAX-Library for building E(3)-equivariant deep learning architectures based on Flax.
Keywords: equivariance,equivariant,invariance,invariant,E(3),SE(3),O(3),SO(3),Euclidean,Orthogonal,group,translation,translational,rotation,rotational,roto-translation,roto-translational,reflection,neural network,machine learning,deep learning
Author-email: The e3x Authors <qcml@google.com>
Requires-Python: >=3.9
Classifier: Programming Language :: Python :: 3
Classifier: Programming Language :: Python :: 3 :: Only
Classifier: License :: OSI Approved :: Apache Software License
Classifier: Intended Audience :: Science/Research
Requires-Dist: absl-py
Requires-Dist: etils[epath]
Requires-Dist: flax
Requires-Dist: jax
Requires-Dist: jaxtyping
Requires-Dist: more_itertools
Requires-Dist: numpy
Requires-Dist: sympy
Requires-Dist: pytest ; extra == "dev"
Requires-Dist: pytest-xdist ; extra == "dev"
Requires-Dist: pylint>=2.6.0 ; extra == "dev"
Requires-Dist: yapf ; extra == "dev"
Requires-Dist: sphinx==7.2.6 ; extra == "dev"
Requires-Dist: sphinx-autodoc-typehints==1.25.2 ; extra == "dev"
Requires-Dist: sphinx-rtd-theme==2.0.0 ; extra == "dev"
Requires-Dist: nbsphinx==0.9.3 ; extra == "dev"
Requires-Dist: jupyter_sphinx==0.5.3 ; extra == "dev"
Requires-Dist: ipykernel==6.29.0 ; extra == "dev"
Requires-Dist: pypandoc_binary==1.12 ; extra == "dev"
Requires-Dist: matplotlib==3.4.3 ; extra == "dev"
Project-URL: homepage, https://github.com/google-research/e3x
Project-URL: repository, https://github.com/google-research/e3x
Provides-Extra: dev
